fds/__init__.py
fds/sdk/__init__.py
fds/sdk/OptimizationEngineAPIMultiperiod/__init__.py
fds/sdk/OptimizationEngineAPIMultiperiod/api_client.py
fds/sdk/OptimizationEngineAPIMultiperiod/configuration.py
fds/sdk/OptimizationEngineAPIMultiperiod/exceptions.py
fds/sdk/OptimizationEngineAPIMultiperiod/model_utils.py
fds/sdk/OptimizationEngineAPIMultiperiod/rest.py
fds/sdk/OptimizationEngineAPIMultiperiod/api/__init__.py
fds/sdk/OptimizationEngineAPIMultiperiod/api/default_api.py
fds/sdk/OptimizationEngineAPIMultiperiod/apis/__init__.py
fds/sdk/OptimizationEngineAPIMultiperiod/model/__init__.py
fds/sdk/OptimizationEngineAPIMultiperiod/model/google_protobuf_list_value.py
fds/sdk/OptimizationEngineAPIMultiperiod/model/google_protobuf_null_value.py
fds/sdk/OptimizationEngineAPIMultiperiod/model/google_protobuf_struct.py
fds/sdk/OptimizationEngineAPIMultiperiod/model/google_protobuf_value.py
fds/sdk/OptimizationEngineAPIMultiperiod/model/optimizer_inputs_across_periods.py
fds/sdk/OptimizationEngineAPIMultiperiod/model/optimizer_inputs_across_periods_rolling_periods.py
fds/sdk/OptimizationEngineAPIMultiperiod/model/optimizer_inputs_asset.py
fds/sdk/OptimizationEngineAPIMultiperiod/model/optimizer_inputs_asset_price.py
fds/sdk/OptimizationEngineAPIMultiperiod/model/optimizer_inputs_asset_price_e_price_source.py
fds/sdk/OptimizationEngineAPIMultiperiod/model/optimizer_inputs_bound_source_enum.py
fds/sdk/OptimizationEngineAPIMultiperiod/model/optimizer_inputs_buy_list_item.py
fds/sdk/OptimizationEngineAPIMultiperiod/model/optimizer_inputs_composite_asset.py
fds/sdk/OptimizationEngineAPIMultiperiod/model/optimizer_inputs_composite_constituent.py
fds/sdk/OptimizationEngineAPIMultiperiod/model/optimizer_inputs_constraint_group.py
fds/sdk/OptimizationEngineAPIMultiperiod/model/optimizer_inputs_constraints.py
fds/sdk/OptimizationEngineAPIMultiperiod/model/optimizer_inputs_dense_matrix.py
fds/sdk/OptimizationEngineAPIMultiperiod/model/optimizer_inputs_derivative.py
fds.sdk.OptimizationEngineAPIMultiperiod-0.21.14.dist-info/LICENSE
fds.sdk.OptimizationEngineAPIMultiperiod-0.21.14.dist-info/METADATA
fds.sdk.OptimizationEngineAPIMultiperiod-0.21.14.dist-info/WHEEL
fds.sdk.OptimizationEngineAPIMultiperiod-0.21.14.dist-info/top_level.txt
fds.sdk.OptimizationEngineAPIMultiperiod-0.21.14.dist-info/RECORD
